loam/__init__.py
loam/_internal.py
loam/_version.py
loam/base.py
loam/cli.py
loam/collections.py
loam/error.py
loam/parsers.py
loam/py.typed
loam/tools.py
loam-0.8.0.dist-info/LICENSE
loam-0.8.0.dist-info/METADATA
loam-0.8.0.dist-info/WHEEL
loam-0.8.0.dist-info/top_level.txt
loam-0.8.0.dist-info/RECORD
