Metadata-Version: 2.1
Name: loam
Version: 0.8.0
Summary: Light configuration manager
Author-email: Adrien Morison <adrien.morison@gmail.com>
Maintainer-email: Adrien Morison <adrien.morison@gmail.com>
License: MIT License
Project-URL: homepage, https://github.com/amorison/loam
Classifier: Development Status :: 4 - Beta
Classifier: Intended Audience :: Developers
Classifier: License :: OSI Approved :: MIT License
Classifier: Programming Language :: Python :: 3 :: Only
Classifier: Programming Language :: Python :: 3.8
Classifier: Programming Language :: Python :: 3.9
Classifier: Programming Language :: Python :: 3.10
Classifier: Programming Language :: Python :: 3.11
Requires-Python: >=3.8
License-File: LICENSE
Requires-Dist: toml (>=0.10.2)
